MANIFEST.in
README.rst
setup.py
bin/qsctl
bin/qsctl.cmd
qingstor/__init__.py
qingstor/qsctl/__init__.py
qingstor/qsctl/constants.py
qingstor/qsctl/driver.py
qingstor/qsctl/utils.py
qingstor/qsctl/commands/__init__.py
qingstor/qsctl/commands/base.py
qingstor/qsctl/commands/cp.py
qingstor/qsctl/commands/ls.py
qingstor/qsctl/commands/mb.py
qingstor/qsctl/commands/mv.py
qingstor/qsctl/commands/rb.py
qingstor/qsctl/commands/rm.py
qingstor/qsctl/commands/sync.py
qingstor/qsctl/commands/transfer.py
qingstor/qsctl/helper/__init__.py
qingstor/qsctl/helper/qsdocutils.py
qingstor/qsctl/helper/textwriter.py
qingstor/qsctl/helper/source/qsctl-cp.rst
qingstor/qsctl/helper/source/qsctl-ls.rst
qingstor/qsctl/helper/source/qsctl-mb.rst
qingstor/qsctl/helper/source/qsctl-mv.rst
qingstor/qsctl/helper/source/qsctl-rb.rst
qingstor/qsctl/helper/source/qsctl-rm.rst
qingstor/qsctl/helper/source/qsctl-sync.rst
qingstor/qsctl/helper/source/qsctl.rst
test/__init__.py
test/test_utils.py
testqsctl.egg-info/PKG-INFO
testqsctl.egg-info/SOURCES.txt
testqsctl.egg-info/dependency_links.txt
testqsctl.egg-info/namespace_packages.txt
testqsctl.egg-info/requires.txt
testqsctl.egg-info/top_level.txt