Metadata-Version: 1.0
Name: testqsctl
Version: 1.4
Summary: Advanced command line tool for QingStor.
Home-page: https://docs.qingcloud.com
Author: Daniel Zheng
Author-email: daniel@yunify.com
License: UNKNOWN
Keywords: qingcloud qingstor qsctl
Platform: UNKNOWN
